strnaming/__init__.py
strnaming/__main__.py
strnaming/classes.py
strnaming/html.py
strnaming/length_adjustments.py
strnaming/libsequence.py
strnaming/libstrnaming.py
strnaming/reference_structures.py
strnaming/refseq_analysis.py
strnaming/refseq_cache.py
strnaming/strnaming.py
strnaming/data/ranges_uas-frr.txt
strnaming/data/reference-structures-1.bin.gz
strnaming/data/reference-structures-10.bin.gz
strnaming/data/reference-structures-11.bin.gz
strnaming/data/reference-structures-12.bin.gz
strnaming/data/reference-structures-13.bin.gz
strnaming/data/reference-structures-14.bin.gz
strnaming/data/reference-structures-15.bin.gz
strnaming/data/reference-structures-16.bin.gz
strnaming/data/reference-structures-17.bin.gz
strnaming/data/reference-structures-18.bin.gz
strnaming/data/reference-structures-19.bin.gz
strnaming/data/reference-structures-2.bin.gz
strnaming/data/reference-structures-20.bin.gz
strnaming/data/reference-structures-21.bin.gz
strnaming/data/reference-structures-22.bin.gz
strnaming/data/reference-structures-3.bin.gz
strnaming/data/reference-structures-4.bin.gz
strnaming/data/reference-structures-5.bin.gz
strnaming/data/reference-structures-6.bin.gz
strnaming/data/reference-structures-7.bin.gz
strnaming/data/reference-structures-8.bin.gz
strnaming/data/reference-structures-9.bin.gz
strnaming/data/reference-structures-X.bin.gz
strnaming/data/reference-structures-Y.bin.gz
strnaming/data/refseq-1-18780.txt.gz
strnaming/data/refseq-10-10521.txt.gz
strnaming/data/refseq-10-10522.txt.gz
strnaming/data/refseq-11-176.txt.gz
strnaming/data/refseq-12-1000.txt.gz
strnaming/data/refseq-12-486.txt.gz
strnaming/data/refseq-13-6685.txt.gz
strnaming/data/refseq-15-7880.txt.gz
strnaming/data/refseq-16-7027.txt.gz
strnaming/data/refseq-17-6077.txt.gz
strnaming/data/refseq-18-5149.txt.gz
strnaming/data/refseq-19-2435.txt.gz
strnaming/data/refseq-2-121.txt.gz
strnaming/data/refseq-2-17742.txt.gz
strnaming/data/refseq-2-5534.txt.gz
strnaming/data/refseq-20-368.txt.gz
strnaming-1.2.0.dist-info/LICENSE-LESSER.txt
strnaming-1.2.0.dist-info/LICENSE.txt
strnaming-1.2.0.dist-info/METADATA
strnaming-1.2.0.dist-info/WHEEL
strnaming-1.2.0.dist-info/entry_points.txt
strnaming-1.2.0.dist-info/top_level.txt
strnaming-1.2.0.dist-info/RECORD
