Metadata-Version: 2.1
Name: strnaming
Version: 1.2.0
Summary: STRNaming STR Sequence Nomenclature
Home-page: https://fdstools.nl
Author: Jerry Hoogenboom
Author-email: jerryhoogenboom@outlook.com
License: LGPLv3+
Project-URL: Bug Tracker, https://github.com/Jerrythafast/STRNaming/issues
Project-URL: Source Code, https://github.com/Jerrythafast/STRNaming
Keywords: bioinformatics forensics NGS MPS DNA sequencing STR nomenclature
Classifier: Programming Language :: Python :: 3
Classifier: License :: OSI Approved :: GNU Lesser General Public License v3 or later (LGPLv3+)
Classifier: Operating System :: OS Independent
Classifier: Development Status :: 4 - Beta
Classifier: Intended Audience :: Science/Research
Classifier: Intended Audience :: Legal Industry
Classifier: Topic :: Scientific/Engineering :: Bio-Informatics
Requires-Python: >=3.5
License-File: LICENSE-LESSER.txt
License-File: LICENSE.txt
